LICENSE
MANIFEST.in
README.md
changelog.md
requirements.txt
setup.py
bin/ep
bin/eppy
epw/__init__.py
epw/cmds.py
epw/displayops.py
epw/einit.py
epw/epprocess.py
epw/__pycache__/__init__.cpython-36.pyc
epw/__pycache__/cmds.cpython-36.pyc
epw/__pycache__/displayops.cpython-36.pyc
epw/__pycache__/einit.cpython-36.pyc
epw/__pycache__/epprocess.cpython-36.pyc
essential_pathway.egg-info/PKG-INFO
essential_pathway.egg-info/SOURCES.txt
essential_pathway.egg-info/dependency_links.txt
essential_pathway.egg-info/requires.txt
essential_pathway.egg-info/top_level.txt