Metadata-Version: 1.1
Name: essential-pathway
Version: 1.0.2
Summary: Manage your most commonly used directories in command line, requires the tcl edition Environment Module.
Home-page: https://github.com/realasking/essential-pathway
Author: realasking
Author-email: realasking@gmail.com,tomwangsim@163.com
License: UNKNOWN
Keywords: ep,epw,environment variables,path,pathway,essential pathway
Platform: linux
Platform: cygwin
Platform: freebsd
Platform: Unix
Classifier: Programming Language :: Python :: 3
Classifier: Topic :: Utilities
Classifier: License :: OSI Approved :: GNU Lesser General Public License v3 (LGPLv3)
Classifier: Development Status :: 5 - Production/Stable
